npdoc_to_md/__init__.py
npdoc_to_md/_version.py
npdoc_to_md/core.py
npdoc_to_md/exceptions.py
npdoc_to_md/helpers.py
npdoc_to_md/logger.py
npdoc_to_md/testing.py
npdoc_to_md/utils.py
npdoc_to_md-1.1.dist-info/LICENSE
npdoc_to_md-1.1.dist-info/METADATA
npdoc_to_md-1.1.dist-info/WHEEL
npdoc_to_md-1.1.dist-info/top_level.txt
npdoc_to_md-1.1.dist-info/RECORD
