Metadata-Version: 2.1
Name: npdoc-to-md
Version: 1.1
Summary: Easy conversion of Python docstrings in numpy style to markdown! Includes a Markdown renderer.
Home-page: https://github.com/ThibTrip/npdoc_to_md
Author: Thibault Bétrémieux
Author-email: thibault.betremieux@gmail.com
License: The Unlicense
Download-URL: https://github.com/ThibTrip/npdoc_to_md/archive/v1.1.tar.gz
Keywords: numpydoc,documentation,docstrings,python
Platform: UNKNOWN
Classifier: Development Status :: 5 - Production/Stable
Classifier: Programming Language :: Python :: 3
Classifier: Programming Language :: Python :: 3.6
Classifier: Programming Language :: Python :: 3.7
Classifier: Programming Language :: Python :: 3.8
Classifier: License :: Public Domain
Classifier: Intended Audience :: Developers
Classifier: Operating System :: OS Independent
Requires-Dist: numpydoc
